noolite_serial/__init__.py
noolite_serial/command.py
noolite_serial/const.py
noolite_serial/noolite.py
noolite_serial-0.1.14.dist-info/METADATA
noolite_serial-0.1.14.dist-info/WHEEL
noolite_serial-0.1.14.dist-info/top_level.txt
noolite_serial-0.1.14.dist-info/RECORD
